PyLogicGates/__init__.py
PyLogicGates-0.0.1.dist-info/LICENSE.txt
PyLogicGates-0.0.1.dist-info/METADATA
PyLogicGates-0.0.1.dist-info/WHEEL
PyLogicGates-0.0.1.dist-info/top_level.txt
PyLogicGates-0.0.1.dist-info/RECORD
