Metadata-Version: 2.1
Name: PyLogicGates
Version: 0.0.1
Summary: use logic gates in python
Home-page: https://github.com/B00bleaTea/PyLogicGates
Author: B00bleTeA
Author-email: asnojus039@gmail.com
License: UNKNOWN
Platform: UNKNOWN
Classifier: Programming Language :: Python :: 3
Classifier: License :: OSI Approved :: MIT License
Classifier: Operating System :: OS Independent
Requires-Python: >=3.8
